Metadata-Version: 1.0
Name: pyGauBin
Version: 0.1
Summary: Gaussian distributions
Home-page: UNKNOWN
Author: Ayse Bat
Author-email: UNKNOWN
License: UNKNOWN
Platform: UNKNOWN
